reminder_aggregator/__init__.py
reminder_aggregator/__main__.py
reminder_aggregator/cli.py
reminder_aggregator/scanner.py
reminder_aggregator-0.3.0.dist-info/METADATA
reminder_aggregator-0.3.0.dist-info/WHEEL
reminder_aggregator-0.3.0.dist-info/entry_points.txt
reminder_aggregator-0.3.0.dist-info/licenses/LICENSE
reminder_aggregator-0.3.0.dist-info/RECORD
